ginsim_setup.py
biolqm/__init__.py
biolqm/jupyter.py
ginsim/__init__.py
ginsim/gateway.py
ginsim/jupyter.py
ginsim/state.py
ginsim-0.4.6.dist-info/METADATA
ginsim-0.4.6.dist-info/WHEEL
ginsim-0.4.6.dist-info/top_level.txt
ginsim-0.4.6.dist-info/RECORD
