Metadata-Version: 2.4
Name: ginsim
Version: 0.4.6
Summary: Python interface to GINsim and BioLQM API
Home-page: https://github.com/GINsim/GINsim-python
Author: Aurélien Naldi
Author-email: aurelien.naldi@gmail.com
Keywords: computational systems biology
Classifier: Intended Audience :: Science/Research
Classifier: Topic :: Scientific/Engineering :: Bio-Informatics
Requires-Dist: py4j
Requires-Dist: colomoto_jupyter>=0.9
Dynamic: author
Dynamic: author-email
Dynamic: classifier
Dynamic: description
Dynamic: home-page
Dynamic: keywords
Dynamic: requires-dist
Dynamic: summary
